accio/Assert.py
accio/Consts.py
accio/Email.py
accio/Excel.py
accio/Http.py
accio/Log.py
accio/Session.py
accio/Shell.py
accio/Strtools.py
accio/__init__.py
accio/analysis_dubbo.py
accio/analysis_har.py
accio/analysis_jmx.py
accio/analysis_openapi.py
accio/analysis_postmanjson.py
accio/analysis_swagger.py
accio/case_generate.py
accio/case_parameter.py
accio/config_file_parser.py
accio/conn_influxdb.py
accio/locust_creat_templatefile.py
accio/locust_get_runlog.py
accio/locust_read_csv.py
accio/locust_read_parameterfile.py
accio/locust_run.py
accio/module_detection.py
accio/parse_tools.py
accio/return_code.py
accio/timed_tasks.py
accioapi-1.2.8.dist-info/COPYING.txt
accioapi-1.2.8.dist-info/METADATA
accioapi-1.2.8.dist-info/WHEEL
accioapi-1.2.8.dist-info/top_level.txt
accioapi-1.2.8.dist-info/zip-safe
accioapi-1.2.8.dist-info/RECORD
