Metadata-Version: 2.1
Name: accioapi
Version: 1.2.8
Summary: this is a api test framework.
Home-page: http://blog.csdn.net/crisschan
Author: CrissChan
Author-email: can101208@gmail.com
License: MIT
Keywords: accioapi python package
Platform: UNKNOWN
Classifier: License :: OSI Approved :: MIT License
Classifier: Development Status :: 5 - Production/Stable
Classifier: Environment :: Console
Classifier: Environment :: Console :: Curses
Classifier: Operating System :: MacOS :: MacOS X
Classifier: Operating System :: POSIX
Classifier: Programming Language :: Python
Classifier: Programming Language :: Python :: 3.5
Classifier: Programming Language :: Python :: 3.6
Classifier: Programming Language :: Python :: 3.7
Classifier: Programming Language :: Python :: Implementation :: CPython
Classifier: Programming Language :: Python :: Implementation :: PyPy
Classifier: Topic :: Internet
Classifier: Topic :: Internet :: WWW/HTTP
Classifier: Topic :: Software Development :: Testing
Requires-Dist: requests (==2.24.0)
Requires-Dist: requests-toolbelt (==0.9.1)
Requires-Dist: allure-pytest (==2.8.18)
Requires-Dist: pytest (==6.0.1)
Requires-Dist: xlrd (==1.2.0)
Requires-Dist: xlwt (==1.3.0)
Requires-Dist: PyYAML (==5.3.1)
Requires-Dist: pytest-rerunfailures (==9.1)
Requires-Dist: pytest-html (==2.1.1)
Requires-Dist: influxdb (==5.3.1)
